{"cameraMode":{"drawMode":0,"name":"Shaded","section":"Shading Mode"},"sceneLighting":true,"audioPlay":false,"sceneViewState":{"m_AlwaysRefresh":false,"showFog":true,"showSkybox":true,"showFlares":true,"showImageEffects":true,"showParticleSystems":true,"showVisualEffectGraphs":true,"m_FxEnabled":true},"in2DMode":false,"pivot":{"x":9.663402557373047,"y":-4.306760311126709,"z":-10.298768997192383},"rotation":{"x":-0.15945319831371308,"y":-0.5677579045295715,"z":0.11319292336702347,"w":-0.7996593713760376},"size":11.369436264038086,"orthographic":false}